setup.py
distributions_AnishPratheepkumar/Binomialdistribution.py
distributions_AnishPratheepkumar/Gaussiandistribution.py
distributions_AnishPratheepkumar/Generaldistribution.py
distributions_AnishPratheepkumar/__init__.py
distributions_AnishPratheepkumar.egg-info/PKG-INFO
distributions_AnishPratheepkumar.egg-info/SOURCES.txt
distributions_AnishPratheepkumar.egg-info/dependency_links.txt
distributions_AnishPratheepkumar.egg-info/not-zip-safe
distributions_AnishPratheepkumar.egg-info/top_level.txt